pvecontrol/__init__.py
pvecontrol/__main__.py
pvecontrol/cli.py
pvecontrol/config.py
pvecontrol/config_default.yaml
pvecontrol/utils.py
pvecontrol/actions/__init__.py
pvecontrol/actions/cluster.py
pvecontrol/actions/node.py
pvecontrol/actions/storage.py
pvecontrol/actions/task.py
pvecontrol/actions/vm.py
pvecontrol/models/__init__.py
pvecontrol/models/backup_job.py
pvecontrol/models/cluster.py
pvecontrol/models/node.py
pvecontrol/models/storage.py
pvecontrol/models/task.py
pvecontrol/models/vm.py
pvecontrol/models/volume.py
pvecontrol/sanitycheck/__init__.py
pvecontrol/sanitycheck/checks.py
pvecontrol/sanitycheck/sanitychecks.py
pvecontrol/sanitycheck/tests/__init__.py
pvecontrol/sanitycheck/tests/ha_groups.py
pvecontrol/sanitycheck/tests/ha_vms.py
pvecontrol/sanitycheck/tests/nodes.py
pvecontrol/sanitycheck/tests/vm.py
pvecontrol/sanitycheck/tests/vm_backups.py
tests/__init__.py
tests/test_backup_job.py
tests/test_cluster.py
tests/test_pvecontrol.py
tests/test_utils.py
tests/testcase.py
tests/sanitycheck/__init__.py
tests/sanitycheck/test_vm_backups.py
tests/sanitycheck/test_vm_disks.py
tests/sanitycheck/utils.py
pvecontrol-0.6.1.dist-info/METADATA
pvecontrol-0.6.1.dist-info/WHEEL
pvecontrol-0.6.1.dist-info/entry_points.txt
pvecontrol-0.6.1.dist-info/top_level.txt
pvecontrol-0.6.1.dist-info/RECORD
