Metadata-Version: 2.4
Name: pvecontrol
Version: 0.6.1
Summary: Proxmox VE control
Author: Laurent Corbes
Author-email: laurent.corbes@enix.fr
Requires-Python: >=3.9
Requires-Dist: prettytable
Requires-Dist: humanize
Requires-Dist: confuse
Requires-Dist: pyyaml
Requires-Dist: urllib3
Requires-Dist: shtab
Requires-Dist: click
Requires-Dist: proxmoxer>=2.0.1
Requires-Dist: requests
Requires-Dist: requests_toolbelt
Requires-Dist: openssh_wrapper
Requires-Dist: paramiko
